jaxmsst/__init__.py
jaxmsst/bsr_dataset.py
jaxmsst/convert.py
jaxmsst/infer.py
jaxmsst/make_dataset.py
jaxmsst/multihost_dataloading.py
jaxmsst/profiling.py
jaxmsst/train.py
jaxmsst/webui.py
jaxmsst/configs/__init__.py
jaxmsst/models/bs_roformer.py
jaxmsst/models/mel_band_roformer.py
jaxmsst-0.1.0.dist-info/licenses/LICENSE
jaxmsst-0.1.0.dist-info/METADATA
jaxmsst-0.1.0.dist-info/WHEEL
jaxmsst-0.1.0.dist-info/top_level.txt
jaxmsst-0.1.0.dist-info/RECORD
