Metadata-Version: 2.4
Name: jaxmsst
Version: 0.1.0
Summary: JAX Music Source Separation Toolkit
Home-page: https://github.com/your-username/jax-Music-Source-Separation
Author: FlyingBlackShark
Author-email: flyingblackshark <aliu2000@outlook.com>
License: MIT License
Project-URL: Homepage, https://github.com/your-username/jax-Music-Source-Separation
Project-URL: Repository, https://github.com/your-username/jax-Music-Source-Separation
Project-URL: Issues, https://github.com/your-username/jax-Music-Source-Separation/issues
Keywords: music,source separation,jax,machine learning,audio processing,transformer
Classifier: Development Status :: 3 - Alpha
Classifier: Intended Audience :: Developers
Classifier: Intended Audience :: Science/Research
Classifier: License :: OSI Approved :: MIT License
Classifier: Operating System :: OS Independent
Classifier: Programming Language :: Python :: 3
Classifier: Programming Language :: Python :: 3.8
Classifier: Programming Language :: Python :: 3.9
Classifier: Programming Language :: Python :: 3.10
Classifier: Programming Language :: Python :: 3.11
Classifier: Topic :: Scientific/Engineering :: Artificial Intelligence
Classifier: Topic :: Multimedia :: Sound/Audio :: Analysis
Requires-Python: >=3.8
License-File: LICENSE
Requires-Dist: jaxlib>=0.4.30
Requires-Dist: flax>=0.10.2
Requires-Dist: optax>=0.2.3
Requires-Dist: argparse
Requires-Dist: einops
Requires-Dist: librosa
Requires-Dist: OmegaConf
Requires-Dist: torch==2.5.1
Requires-Dist: torchvision==0.20.1
Requires-Dist: gradio
Provides-Extra: dev
Requires-Dist: pytest>=6.0; extra == "dev"
Requires-Dist: pytest-cov>=2.0; extra == "dev"
Requires-Dist: black>=21.0; extra == "dev"
Requires-Dist: flake8>=3.8; extra == "dev"
Requires-Dist: mypy>=0.800; extra == "dev"
Provides-Extra: train
Requires-Dist: wandb; extra == "train"
Requires-Dist: tensorboard; extra == "train"
Dynamic: author
Dynamic: home-page
Dynamic: license-file
Dynamic: requires-python
